ifireflylib/__init__.py
ifireflylib/api/__init__.py
ifireflylib/api/exceptions.py
ifireflylib/api/hash_operations.py
ifireflylib/api/list_operations.py
ifireflylib/api/string_operations.py
ifireflylib/client/__init__.py
ifireflylib/client/client.py
ifireflylib/client/utils.py
ifireflylib/examples/__init__.py
ifireflylib/examples/api_example.py
ifireflylib/native/__init__.py
ifireflylib/native/libFireflyClient.dll
ifireflylib/native/libFireflyClient.so
ifireflylib/tests/__init__.py
ifireflylib/tests/test_basic.py
ifireflylib-0.3.0.dist-info/METADATA
ifireflylib-0.3.0.dist-info/WHEEL
ifireflylib-0.3.0.dist-info/top_level.txt
ifireflylib-0.3.0.dist-info/RECORD
