Metadata-Version: 2.4
Name: ifireflylib
Version: 0.3.0
Summary: A client package for Firefly database
Home-page: https://gitea.innovativedevsolutions.org/IDSolutions/ifireflylib
Author: IDSolutions
Author-email: IDSolutions <info@innovativedevsolutions.org>
Project-URL: Homepage, https://gitea.innovativedevsolutions.org/IDSolutions/ifireflylib
Project-URL: Documentation, https://gitea.innovativedevsolutions.org/IDSolutions/ifireflylib#readme
Project-URL: Repository, https://gitea.innovativedevsolutions.org/IDSolutions/ifireflylib.git
Project-URL: Bug Tracker, https://gitea.innovativedevsolutions.org/IDSolutions/ifireflylib/issues
Keywords: firefly,database
Classifier: Development Status :: 4 - Beta
Classifier: Intended Audience :: Developers
Classifier: License :: OSI Approved :: MIT License
Classifier: Operating System :: OS Independent
Classifier: Programming Language :: Python :: 3
Classifier: Programming Language :: Python :: 3.13
Classifier: Topic :: Database
Requires-Python: >=3.13
Dynamic: author
Dynamic: home-page
Dynamic: requires-python
